
[  
  { 
    "id": "1",
    "nombre": "Taylor Swift",
    "imagen": "img/tay.jpeg",
    "genero": "Pop",
    "canciones": [
      {
        "idCancion": "68a6139c41ac8857c890ae28",
        "titulo": "Love Story",
        "duracion": "3:55",
        "video": ""
      },
      {
        "idCancion": "68a6152841ac8857c890ae2c",
        "titulo": "Shake it off",
        "duracion": "3:45",
        "video": ""
      },
      {
        "idCancion": "68a6179641ac8857c890ae2f",
        "titulo": "Blank Space",
        "duracion": "3:52",
        "video": ""
      },
      {
        "idCancion": "68a6192e41ac8857c890ae31",
        "titulo": "Bad Blood",
        "duracion": "3:37",
        "video": ""
      },
      {
        "idCancion": "68a6197c41ac8857c890ae32",
        "titulo": "Cruel Summer",
        "duracion": "3:00",
        "video": ""
      }
      ,
      {
        "idCancion": "68a6197c41ac8857c890ae32",
        "titulo": "You Belong With Me",
        "duracion": "3:52",
        "video": ""
      }
      ,
      {
        "idCancion": "68a6197c41ac8857c890ae32",
        "titulo": "I Knew You Were Trouble",
        "duracion": "3:41",
        "video": ""
      }
      ,
      {
        "idCancion": "68a6197c41ac8857c890ae32",
        "titulo": "Karma",
        "duracion": "3:30",
        "video": ""
      }
      ,
      {
        "idCancion": "68a6197c41ac8857c890ae32",
        "titulo": "Style",
        "duracion": "3:56",
        "video": ""
      }
    ]
  },

  {
    "id": "2",
    "nombre": "Pitbull",
    "imagen": "img/pitbull.jpg",
    "genero": "Pop",
    "canciones": [
      {
        "idCancion": "68a61c5341ac8857c890ae34",
        "titulo": "Give Me Everything",
        "duracion": "4:15",
        "video": ""
      },
      {
        "idCancion": "68a61db141ac8857c890ae35",
        "titulo": "Timber",
        "duracion": "3:23",
        "video": ""
      },
      {
        "idCancion": "68a61ebf41ac8857c890ae36",
        "titulo": "I know you want me (Calle Ocho)",
        "duracion": "3:04",
        "video": ""
      },
      {
        "idCancion": "68af4d765d5beecd476c007f",
        "titulo": "Hotel Room Service",
        "duracion": "4:00",
        "video": ""
      },
      {
        "idCancion": "68af4d765d5beecd476c007f",
        "titulo": "We are one (Ole Ola)",
        "duracion": "3:43",
        "video": ""
      }
    ]
  },
  
  {
    "_id": "68af5a425d5beecd476c008d",
    "nombre": "Justin Bieber",
    "foto": "https://jpg.com/fotoArtista/justin.jpg",
    "genero": "Pop",
    "canciones": [
      {
        "idCancion": "JB1",
        "titulo": "Baby",
        "duracion": "3:39",
        "video": "/home/campanita/Escritorio/Karaoke/videos/Baby.mp4"
      },
      {
        "idCancion": "JB2",
        "titulo": "Peaches",
        "duracion": "3:22",
        "video": "/home/campanita/Escritorio/Karaoke/videos/Baby.mp4"
      },
      {
        "idCancion": "JB3",
        "titulo": "Sorry",
        "duracion": "3:23",
        "video": "/home/campanita/Escritorio/Karaoke/videos/Baby.mp4"
      },
      {
        "idCanicion": "JB4",
        "titulo": "Love Yourself",
        "duracion": "4:01",
        "video": "/home/campanita/Escritorio/Karaoke/videos/Baby.mp4"
      }
    ]
  },
{
  "_id": "68af68195d5beecd476c0090",
  "nombre": "Ariana Grande",
  "foto": "https://jpg.com/fotoArtista/ariana.jpg",
  "genero": "Pop",
  "canciones": [
    {
      "idCancion": "AG1",
      "titulo": "The Boy Is Mine",
      "duracion": "3:01",
      "video": "/home/campanita/Escritorio/Karaoke/videos/TheBoyIsMine.mp4"
    },
    {
      "idCancion": "AG2",
      "titulo": "7 Rings",
      "duracion": "2:57",
      "video": "/home/campanita/Escritorio/Karaoke/videos/7rings.mp4"
    },
    {
      "idCancion": "AG3",
      "titulo": "thank u, next",
      "duracion": "3:36",
      "video": "/home/campanita/Escritorio/Karaoke/videos/ThankUNext.mp4"
    },
    {
      "titulo": "yes, and?",
      "duracion": "3:41",
      "video": "/home/campanita/Escritorio/Karaoke/videos/YesAnd.mp4",
      "idCancion": "AG4"
    },
    {
      "titulo": "Break Free",
      "duracion": "3:44",
      "video": "/home/campanita/Escritorio/Karaoke/videos/BreakFree.mp4",
      "idCancion": "AG5"
    },
    {
      "titulo": "Dangerous Woman",
      "duracion": "4:02",
      "video": "/home/campanita/Escritorio/Karaoke/videos/DangerousWoman.mp4",
      "idCancion": "AG6"
    }
  ]
}
]